README.rst
httpie_msgpack.py
setup.py
httpie_msgpack.egg-info/PKG-INFO
httpie_msgpack.egg-info/SOURCES.txt
httpie_msgpack.egg-info/dependency_links.txt
httpie_msgpack.egg-info/entry_points.txt
httpie_msgpack.egg-info/not-zip-safe
httpie_msgpack.egg-info/requires.txt
httpie_msgpack.egg-info/top_level.txt